macropad/CustomLP.py
macropad/__init__.py
macropad/setup.py
macropad-1.1.1.dist-info/LICENSE.txt
macropad-1.1.1.dist-info/METADATA
macropad-1.1.1.dist-info/WHEEL
macropad-1.1.1.dist-info/top_level.txt
macropad-1.1.1.dist-info/RECORD
