Metadata-Version: 2.1
Name: macropad
Version: 1.1.1
Summary: Use the Launchpad-Mk2 as a Macro Device
Home-page: UNKNOWN
Author: LiquidDevect
Author-email: 
License: UNKNOWN
Platform: UNKNOWN
Classifier: Programming Language :: Python :: 3
Classifier: License :: OSI Approved :: MIT License
Classifier: Operating System :: OS Independent
Requires-Python: >= 3
